genieml/__init__.py
genieml-0.0.1.dev0.dist-info/METADATA
genieml-0.0.1.dev0.dist-info/WHEEL
genieml-0.0.1.dev0.dist-info/top_level.txt
genieml-0.0.1.dev0.dist-info/RECORD
