Metadata-Version: 2.1
Name: genieml
Version: 0.0.1.dev0
Summary: genieml
Author: Henry Fuheng Wu
Keywords: genieml
Classifier: Programming Language :: Python :: 3
Classifier: Programming Language :: Python :: 3.8
Classifier: Programming Language :: Python :: 3.9
Classifier: Programming Language :: Python :: 3.10
Classifier: Programming Language :: Python :: 3.11
